{
  "parent": "minecraft:story/root",
  "criteria": {
    "get_stone": {
      "conditions": {
        "items": [
          {
            "tag": "minecraft:stone_tool_materials"
          }
        ]
      },
      "trigger": "minecraft:inventory_changed"
    }
  },
  "display": {
    "announce_to_chat": true,
    "description": {
      "text": "Mine a stone block with your bare hands"
    },
    "frame": "task",
    "hidden": false,
    "icon": {
      "item": "minecraft:cobblestone"
    },
    "show_toast": true,
    "title": {
      "text": "Rock & Stone!"
    }
  },
  "requirements": [
    [
      "get_stone"
    ]
  ],
  "sends_telemetry_event": true
}