{
  "parent": "minecraft:recipes/root",
  "rewards": {
    "recipes": [
      "everycomp:abnbl/quark/large_azalea_boat"
    ]
  },
  "criteria": {
    "has_item": {
      "trigger": "minecraft:inventory_changed",
      "conditions": {
        "player": null,
        "items": [
          {
            "items": [
              "quark:azalea_planks"
            ],
            "count": null,
            "durability": null,
            "nbt": null
          }
        ]
      }
    },
    "has_the_recipe": {
      "trigger": "minecraft:recipe_unlocked",
      "conditions": {
        "player": null,
        "recipe": "everycomp:abnbl/quark/large_azalea_boat"
      }
    }
  },
  "requirements": [
    [
      "has_item",
      "has_the_recipe"
    ]
  ],
  "sends_telemetry_event": false
}